pyedgar/__init__.py
pyedgar/config.py
pyedgar/downloader.py
pyedgar/exceptions.py
pyedgar/filing.py
pyedgar/index.py
pyedgar/pyedgar.conf
pyedgar/utilities/__init__.py
pyedgar/utilities/_html_encoding_lookup.py
pyedgar/utilities/edgarcache.py
pyedgar/utilities/edgarweb.py
pyedgar/utilities/forms.py
pyedgar/utilities/htmlparse.py
pyedgar/utilities/indices.py
pyedgar/utilities/localstore.py
pyedgar/utilities/plaintext.py
pyedgar-0.1.12.dist-info/LICENSE
pyedgar-0.1.12.dist-info/METADATA
pyedgar-0.1.12.dist-info/WHEEL
pyedgar-0.1.12.dist-info/top_level.txt
pyedgar-0.1.12.dist-info/RECORD
