Metadata-Version: 2.2
Name: pyedgar
Version: 0.1.12
Summary: Python interface to EDGAR filings.
Home-page: https://github.com/gaulinmp/pyedgar
Author: Mac Gaulin
Author-email: gaulinmp+pyedgar@gmail.com
License: MIT
Keywords: SEC EDGAR filings
Classifier: Development Status :: 3 - Alpha
Classifier: Environment :: Console
Classifier: Operating System :: OS Independent
Classifier: Intended Audience :: Science/Research
Classifier: Intended Audience :: Education
Classifier: Topic :: Office/Business :: Financial :: Accounting
Classifier: Natural Language :: English
Classifier: License :: OSI Approved :: MIT License
Classifier: Programming Language :: Python :: 3 :: Only
Classifier: Programming Language :: Python :: 3
Classifier: Programming Language :: Python :: 3.4
Classifier: Programming Language :: Python :: 3.5
Classifier: Programming Language :: Python :: 3.6
Classifier: Programming Language :: Python :: 3.7
Classifier: Programming Language :: Python :: 3.8
License-File: LICENSE
Requires-Dist: pandas
Requires-Dist: requests
Provides-Extra: dev
Requires-Dist: bs4; extra == "dev"
Requires-Dist: tqdm; extra == "dev"
Dynamic: author
Dynamic: author-email
Dynamic: classifier
Dynamic: description
Dynamic: description-content-type
Dynamic: home-page
Dynamic: keywords
Dynamic: license
Dynamic: provides-extra
Dynamic: requires-dist
Dynamic: summary
